parler_tts
training
