Metadata-Version: 2.1
Name: parler_tts
Version: 0.2.3
Summary: Toolkit for using and training Parler-TTS, a high-quality text-to-speech model.
License-File: LICENSE
Requires-Dist: transformers<=4.46.1,>=4.46.1
Requires-Dist: torch
Requires-Dist: sentencepiece
Requires-Dist: descript-audio-codec-unofficial
Requires-Dist: descript-audiotools-unofficial
Requires-Dist: protobuf>=4.0.0
Provides-Extra: dev
Requires-Dist: black~=23.1; extra == "dev"
Requires-Dist: isort>=5.5.4; extra == "dev"
Requires-Dist: ruff<=0.0.259,>=0.0.241; extra == "dev"
Provides-Extra: train
Requires-Dist: jiwer; extra == "train"
Requires-Dist: wandb; extra == "train"
Requires-Dist: accelerate; extra == "train"
Requires-Dist: evaluate; extra == "train"
Requires-Dist: datasets[audio]>=2.14.5; extra == "train"
